es-xlsx2csv/__init__.py
es-xlsx2csv/command_line.py
es_xlsx2csv/__init__.py
es_xlsx2csv/command_line.py
es_xlsx2csv-0.0.8.dist-info/LICENSE
es_xlsx2csv-0.0.8.dist-info/METADATA
es_xlsx2csv-0.0.8.dist-info/WHEEL
es_xlsx2csv-0.0.8.dist-info/entry_points.txt
es_xlsx2csv-0.0.8.dist-info/top_level.txt
es_xlsx2csv-0.0.8.dist-info/RECORD
